<root>
  <item name="com.sun.java.swing.plaf.motif.MotifComboBoxUI.MotifComboPopup java.awt.event.KeyListener createKeyListener()">
    <annotation name="org.jetbrains.annotations.Nullable"/>
  </item>
  <item name="com.sun.java.swing.plaf.motif.MotifDesktopPaneUI.MotifDesktopManager javax.swing.JInternalFrame.JDesktopIcon getIconAt(javax.swing.JDesktopPane, javax.swing.JInternalFrame.JDesktopIcon, int, int)">
    <annotation name="org.jetbrains.annotations.Nullable"/>
  </item>
  <item name="com.sun.java.swing.plaf.motif.MotifFileChooserUI java.lang.String fileNameString(java.io.File)">
    <annotation name="org.jetbrains.annotations.Nullable"/>
  </item>
  <item name="com.sun.java.swing.plaf.motif.MotifFileChooserUI java.lang.String getFileName()">
    <annotation name="org.jetbrains.annotations.Nullable"/>
  </item>
  <item name="com.sun.java.swing.plaf.motif.MotifFileChooserUI.FilterComboBoxModel java.lang.Object getElementAt(int)">
    <annotation name="org.jetbrains.annotations.Nullable"/>
  </item>
  <item name="com.sun.java.swing.plaf.motif.MotifIconFactory javax.swing.Icon getMenuItemCheckIcon()">
    <annotation name="org.jetbrains.annotations.Nullable"/>
  </item>
  <item name="com.sun.java.swing.plaf.motif.MotifLookAndFeel.1 java.lang.Object createValue(javax.swing.UIDefaults)">
    <annotation name="org.jetbrains.annotations.Nullable"/>
  </item>
  <item name="com.sun.java.swing.plaf.motif.MotifOptionPaneUI java.awt.Dimension getMinimumOptionPaneSize()">
    <annotation name="org.jetbrains.annotations.Nullable"/>
  </item>
  <item name="com.sun.java.swing.plaf.motif.MotifPopupMenuUI java.awt.Dimension getPreferredSize(javax.swing.JComponent)">
    <annotation name="org.jetbrains.annotations.Nullable"/>
  </item>
</root>
