<root>
  <item name="com.sun.xml.internal.fastinfoset.vocab.ParserVocabulary ParserVocabulary(com.sun.xml.internal.org.jvnet.fastinfoset.Vocabulary) 0">
    <annotation name="org.jetbrains.annotations.NotNull"/>
  </item>
  <item name="com.sun.xml.internal.fastinfoset.vocab.ParserVocabulary int getIntegerValueFromProperty(java.lang.String) 0">
    <annotation name="org.jetbrains.annotations.NotNull"/>
  </item>
  <item name="com.sun.xml.internal.fastinfoset.vocab.ParserVocabulary void addToNameTable(javax.xml.namespace.QName, com.sun.xml.internal.fastinfoset.util.QualifiedNameArray, boolean, com.sun.xml.internal.fastinfoset.util.StringIntMap, com.sun.xml.internal.fastinfoset.util.StringIntMap, com.sun.xml.internal.fastinfoset.util.StringIntMap) 0">
    <annotation name="org.jetbrains.annotations.NotNull"/>
  </item>
  <item name="com.sun.xml.internal.fastinfoset.vocab.ParserVocabulary void addToNameTable(javax.xml.namespace.QName, com.sun.xml.internal.fastinfoset.util.QualifiedNameArray, boolean, com.sun.xml.internal.fastinfoset.util.StringIntMap, com.sun.xml.internal.fastinfoset.util.StringIntMap, com.sun.xml.internal.fastinfoset.util.StringIntMap) 1">
    <annotation name="org.jetbrains.annotations.NotNull"/>
  </item>
  <item name="com.sun.xml.internal.fastinfoset.vocab.ParserVocabulary void addToNameTable(javax.xml.namespace.QName, com.sun.xml.internal.fastinfoset.util.QualifiedNameArray, boolean, com.sun.xml.internal.fastinfoset.util.StringIntMap, com.sun.xml.internal.fastinfoset.util.StringIntMap, com.sun.xml.internal.fastinfoset.util.StringIntMap) 5">
    <annotation name="org.jetbrains.annotations.NotNull"/>
  </item>
  <item name="com.sun.xml.internal.fastinfoset.vocab.ParserVocabulary void addToTable(java.lang.String, com.sun.xml.internal.fastinfoset.util.CharArrayArray) 0">
    <annotation name="org.jetbrains.annotations.NotNull"/>
  </item>
  <item name="com.sun.xml.internal.fastinfoset.vocab.ParserVocabulary void addToTable(java.lang.String, com.sun.xml.internal.fastinfoset.util.ContiguousCharArrayArray) 0">
    <annotation name="org.jetbrains.annotations.NotNull"/>
  </item>
  <item name="com.sun.xml.internal.fastinfoset.vocab.ParserVocabulary void addToTable(java.lang.String, com.sun.xml.internal.fastinfoset.util.PrefixArray, com.sun.xml.internal.fastinfoset.util.StringIntMap) 0">
    <annotation name="org.jetbrains.annotations.NotNull"/>
  </item>
  <item name="com.sun.xml.internal.fastinfoset.vocab.ParserVocabulary void addToTable(java.lang.String, com.sun.xml.internal.fastinfoset.util.PrefixArray, com.sun.xml.internal.fastinfoset.util.StringIntMap) 2">
    <annotation name="org.jetbrains.annotations.Nullable"/>
  </item>
  <item name="com.sun.xml.internal.fastinfoset.vocab.ParserVocabulary void addToTable(java.lang.String, com.sun.xml.internal.fastinfoset.util.StringArray, com.sun.xml.internal.fastinfoset.util.StringIntMap) 0">
    <annotation name="org.jetbrains.annotations.NotNull"/>
  </item>
  <item name="com.sun.xml.internal.fastinfoset.vocab.ParserVocabulary void addToTable(java.lang.String, com.sun.xml.internal.fastinfoset.util.StringArray, com.sun.xml.internal.fastinfoset.util.StringIntMap) 2">
    <annotation name="org.jetbrains.annotations.Nullable"/>
  </item>
  <item name="com.sun.xml.internal.fastinfoset.vocab.ParserVocabulary void addToTable(java.util.Iterator, com.sun.xml.internal.fastinfoset.util.CharArrayArray) 0">
    <annotation name="org.jetbrains.annotations.NotNull"/>
  </item>
  <item name="com.sun.xml.internal.fastinfoset.vocab.ParserVocabulary void addToTable(java.util.Iterator, com.sun.xml.internal.fastinfoset.util.ContiguousCharArrayArray) 0">
    <annotation name="org.jetbrains.annotations.NotNull"/>
  </item>
  <item name="com.sun.xml.internal.fastinfoset.vocab.ParserVocabulary void addToTable(java.util.Iterator, com.sun.xml.internal.fastinfoset.util.PrefixArray, com.sun.xml.internal.fastinfoset.util.StringIntMap) 0">
    <annotation name="org.jetbrains.annotations.NotNull"/>
  </item>
  <item name="com.sun.xml.internal.fastinfoset.vocab.ParserVocabulary void addToTable(java.util.Iterator, com.sun.xml.internal.fastinfoset.util.PrefixArray, com.sun.xml.internal.fastinfoset.util.StringIntMap) 2">
    <annotation name="org.jetbrains.annotations.Nullable"/>
  </item>
  <item name="com.sun.xml.internal.fastinfoset.vocab.ParserVocabulary void addToTable(java.util.Iterator, com.sun.xml.internal.fastinfoset.util.QualifiedNameArray, boolean, com.sun.xml.internal.fastinfoset.util.StringIntMap, com.sun.xml.internal.fastinfoset.util.StringIntMap, com.sun.xml.internal.fastinfoset.util.StringIntMap) 0">
    <annotation name="org.jetbrains.annotations.NotNull"/>
  </item>
  <item name="com.sun.xml.internal.fastinfoset.vocab.ParserVocabulary void addToTable(java.util.Iterator, com.sun.xml.internal.fastinfoset.util.StringArray) 0">
    <annotation name="org.jetbrains.annotations.NotNull"/>
  </item>
  <item name="com.sun.xml.internal.fastinfoset.vocab.ParserVocabulary void addToTable(java.util.Iterator, com.sun.xml.internal.fastinfoset.util.StringArray, com.sun.xml.internal.fastinfoset.util.StringIntMap) 0">
    <annotation name="org.jetbrains.annotations.NotNull"/>
  </item>
  <item name="com.sun.xml.internal.fastinfoset.vocab.ParserVocabulary void addToTable(java.util.Iterator, com.sun.xml.internal.fastinfoset.util.StringArray, com.sun.xml.internal.fastinfoset.util.StringIntMap) 2">
    <annotation name="org.jetbrains.annotations.Nullable"/>
  </item>
  <item name="com.sun.xml.internal.fastinfoset.vocab.ParserVocabulary void convertVocabulary(com.sun.xml.internal.org.jvnet.fastinfoset.Vocabulary) 0">
    <annotation name="org.jetbrains.annotations.NotNull"/>
  </item>
  <item name="com.sun.xml.internal.fastinfoset.vocab.ParserVocabulary void setReferencedVocabulary(java.lang.String, com.sun.xml.internal.fastinfoset.vocab.ParserVocabulary, boolean) 0">
    <annotation name="org.jetbrains.annotations.NotNull"/>
  </item>
  <item name="com.sun.xml.internal.fastinfoset.vocab.SerializerVocabulary SerializerVocabulary(com.sun.xml.internal.org.jvnet.fastinfoset.Vocabulary, boolean) 0">
    <annotation name="org.jetbrains.annotations.NotNull"/>
  </item>
  <item name="com.sun.xml.internal.fastinfoset.vocab.SerializerVocabulary void addToNameTable(javax.xml.namespace.QName, com.sun.xml.internal.fastinfoset.util.LocalNameQualifiedNamesMap) 0">
    <annotation name="org.jetbrains.annotations.NotNull"/>
  </item>
  <item name="com.sun.xml.internal.fastinfoset.vocab.SerializerVocabulary void addToNameTable(javax.xml.namespace.QName, com.sun.xml.internal.fastinfoset.util.LocalNameQualifiedNamesMap) 1">
    <annotation name="org.jetbrains.annotations.NotNull"/>
  </item>
  <item name="com.sun.xml.internal.fastinfoset.vocab.SerializerVocabulary void addToTable(java.lang.String, com.sun.xml.internal.fastinfoset.util.CharArrayIntMap) 0">
    <annotation name="org.jetbrains.annotations.NotNull"/>
  </item>
  <item name="com.sun.xml.internal.fastinfoset.vocab.SerializerVocabulary void addToTable(java.lang.String, com.sun.xml.internal.fastinfoset.util.StringIntMap) 0">
    <annotation name="org.jetbrains.annotations.NotNull"/>
  </item>
  <item name="com.sun.xml.internal.fastinfoset.vocab.SerializerVocabulary void addToTable(java.util.Iterator, com.sun.xml.internal.fastinfoset.util.CharArrayIntMap) 0">
    <annotation name="org.jetbrains.annotations.NotNull"/>
  </item>
  <item name="com.sun.xml.internal.fastinfoset.vocab.SerializerVocabulary void addToTable(java.util.Iterator, com.sun.xml.internal.fastinfoset.util.LocalNameQualifiedNamesMap) 0">
    <annotation name="org.jetbrains.annotations.NotNull"/>
  </item>
  <item name="com.sun.xml.internal.fastinfoset.vocab.SerializerVocabulary void addToTable(java.util.Iterator, com.sun.xml.internal.fastinfoset.util.StringIntMap) 0">
    <annotation name="org.jetbrains.annotations.NotNull"/>
  </item>
  <item name="com.sun.xml.internal.fastinfoset.vocab.SerializerVocabulary void convertVocabulary(com.sun.xml.internal.org.jvnet.fastinfoset.Vocabulary) 0">
    <annotation name="org.jetbrains.annotations.NotNull"/>
  </item>
</root>
