<root>
  <item name="com.sun.imageio.spi.FileImageInputStreamSpi java.lang.String getDescription(java.util.Locale) 0">
    <annotation name="org.jetbrains.annotations.Nullable"/>
  </item>
  <item name="com.sun.imageio.spi.FileImageInputStreamSpi java.lang.String getDescription(java.util.Locale)">
    <annotation name="org.jetbrains.annotations.NotNull"/>
    <annotation name="org.jetbrains.annotations.Pure"/>
  </item>
  <item name="com.sun.imageio.spi.FileImageInputStreamSpi javax.imageio.stream.ImageInputStream createInputStreamInstance(java.lang.Object, boolean, java.io.File) 0">
    <annotation name="org.jetbrains.annotations.NotNull"/>
  </item>
  <item name="com.sun.imageio.spi.FileImageInputStreamSpi javax.imageio.stream.ImageInputStream createInputStreamInstance(java.lang.Object, boolean, java.io.File) 2">
    <annotation name="org.jetbrains.annotations.Nullable"/>
  </item>
  <item name="com.sun.imageio.spi.FileImageOutputStreamSpi java.lang.String getDescription(java.util.Locale) 0">
    <annotation name="org.jetbrains.annotations.Nullable"/>
  </item>
  <item name="com.sun.imageio.spi.FileImageOutputStreamSpi java.lang.String getDescription(java.util.Locale)">
    <annotation name="org.jetbrains.annotations.NotNull"/>
    <annotation name="org.jetbrains.annotations.Pure"/>
  </item>
  <item name="com.sun.imageio.spi.FileImageOutputStreamSpi javax.imageio.stream.ImageOutputStream createOutputStreamInstance(java.lang.Object, boolean, java.io.File) 0">
    <annotation name="org.jetbrains.annotations.NotNull"/>
  </item>
  <item name="com.sun.imageio.spi.FileImageOutputStreamSpi javax.imageio.stream.ImageOutputStream createOutputStreamInstance(java.lang.Object, boolean, java.io.File) 2">
    <annotation name="org.jetbrains.annotations.Nullable"/>
  </item>
  <item name="com.sun.imageio.spi.InputStreamImageInputStreamSpi boolean canUseCacheFile()">
    <annotation name="org.jetbrains.annotations.Pure"/>
  </item>
  <item name="com.sun.imageio.spi.InputStreamImageInputStreamSpi boolean needsCacheFile()">
    <annotation name="org.jetbrains.annotations.Pure"/>
  </item>
  <item name="com.sun.imageio.spi.InputStreamImageInputStreamSpi java.lang.String getDescription(java.util.Locale) 0">
    <annotation name="org.jetbrains.annotations.Nullable"/>
  </item>
  <item name="com.sun.imageio.spi.InputStreamImageInputStreamSpi java.lang.String getDescription(java.util.Locale)">
    <annotation name="org.jetbrains.annotations.NotNull"/>
    <annotation name="org.jetbrains.annotations.Pure"/>
  </item>
  <item name="com.sun.imageio.spi.InputStreamImageInputStreamSpi javax.imageio.stream.ImageInputStream createInputStreamInstance(java.lang.Object, boolean, java.io.File) 0">
    <annotation name="org.jetbrains.annotations.NotNull"/>
  </item>
  <item name="com.sun.imageio.spi.InputStreamImageInputStreamSpi javax.imageio.stream.ImageInputStream createInputStreamInstance(java.lang.Object, boolean, java.io.File) 2">
    <annotation name="org.jetbrains.annotations.Nullable"/>
  </item>
  <item name="com.sun.imageio.spi.InputStreamImageInputStreamSpi javax.imageio.stream.ImageInputStream createInputStreamInstance(java.lang.Object, boolean, java.io.File)">
    <annotation name="org.jetbrains.annotations.NotNull"/>
  </item>
  <item name="com.sun.imageio.spi.OutputStreamImageOutputStreamSpi boolean canUseCacheFile()">
    <annotation name="org.jetbrains.annotations.Pure"/>
  </item>
  <item name="com.sun.imageio.spi.OutputStreamImageOutputStreamSpi boolean needsCacheFile()">
    <annotation name="org.jetbrains.annotations.Pure"/>
  </item>
  <item name="com.sun.imageio.spi.OutputStreamImageOutputStreamSpi java.lang.String getDescription(java.util.Locale) 0">
    <annotation name="org.jetbrains.annotations.Nullable"/>
  </item>
  <item name="com.sun.imageio.spi.OutputStreamImageOutputStreamSpi java.lang.String getDescription(java.util.Locale)">
    <annotation name="org.jetbrains.annotations.NotNull"/>
    <annotation name="org.jetbrains.annotations.Pure"/>
  </item>
  <item name="com.sun.imageio.spi.OutputStreamImageOutputStreamSpi javax.imageio.stream.ImageOutputStream createOutputStreamInstance(java.lang.Object, boolean, java.io.File) 0">
    <annotation name="org.jetbrains.annotations.NotNull"/>
  </item>
  <item name="com.sun.imageio.spi.OutputStreamImageOutputStreamSpi javax.imageio.stream.ImageOutputStream createOutputStreamInstance(java.lang.Object, boolean, java.io.File) 2">
    <annotation name="org.jetbrains.annotations.Nullable"/>
  </item>
  <item name="com.sun.imageio.spi.OutputStreamImageOutputStreamSpi javax.imageio.stream.ImageOutputStream createOutputStreamInstance(java.lang.Object, boolean, java.io.File)">
    <annotation name="org.jetbrains.annotations.NotNull"/>
  </item>
  <item name="com.sun.imageio.spi.RAFImageInputStreamSpi java.lang.String getDescription(java.util.Locale) 0">
    <annotation name="org.jetbrains.annotations.Nullable"/>
  </item>
  <item name="com.sun.imageio.spi.RAFImageInputStreamSpi java.lang.String getDescription(java.util.Locale)">
    <annotation name="org.jetbrains.annotations.NotNull"/>
    <annotation name="org.jetbrains.annotations.Pure"/>
  </item>
  <item name="com.sun.imageio.spi.RAFImageInputStreamSpi javax.imageio.stream.ImageInputStream createInputStreamInstance(java.lang.Object, boolean, java.io.File) 0">
    <annotation name="org.jetbrains.annotations.NotNull"/>
  </item>
  <item name="com.sun.imageio.spi.RAFImageInputStreamSpi javax.imageio.stream.ImageInputStream createInputStreamInstance(java.lang.Object, boolean, java.io.File) 2">
    <annotation name="org.jetbrains.annotations.Nullable"/>
  </item>
  <item name="com.sun.imageio.spi.RAFImageOutputStreamSpi java.lang.String getDescription(java.util.Locale) 0">
    <annotation name="org.jetbrains.annotations.Nullable"/>
  </item>
  <item name="com.sun.imageio.spi.RAFImageOutputStreamSpi java.lang.String getDescription(java.util.Locale)">
    <annotation name="org.jetbrains.annotations.NotNull"/>
    <annotation name="org.jetbrains.annotations.Pure"/>
  </item>
  <item name="com.sun.imageio.spi.RAFImageOutputStreamSpi javax.imageio.stream.ImageOutputStream createOutputStreamInstance(java.lang.Object, boolean, java.io.File) 0">
    <annotation name="org.jetbrains.annotations.NotNull"/>
  </item>
  <item name="com.sun.imageio.spi.RAFImageOutputStreamSpi javax.imageio.stream.ImageOutputStream createOutputStreamInstance(java.lang.Object, boolean, java.io.File) 2">
    <annotation name="org.jetbrains.annotations.Nullable"/>
  </item>
</root>
