<root>
  <item name="java.rmi.activation.Activatable java.rmi.Remote exportObject(java.rmi.Remote, sun.rmi.server.ActivatableServerRef) 1">
    <annotation name="org.jetbrains.annotations.NotNull"/>
  </item>
  <item name="java.rmi.activation.Activatable java.rmi.Remote register(java.rmi.activation.ActivationDesc) 0">
    <annotation name="org.jetbrains.annotations.NotNull"/>
  </item>
  <item name="java.rmi.activation.Activatable java.rmi.activation.ActivationID exportObject(java.rmi.Remote, java.lang.String, java.rmi.MarshalledObject&lt;?&gt;, boolean, int) 0">
    <annotation name="org.jetbrains.annotations.NotNull"/>
  </item>
  <item name="java.rmi.activation.Activatable java.rmi.activation.ActivationID exportObject(java.rmi.Remote, java.lang.String, java.rmi.MarshalledObject&lt;?&gt;, boolean, int, java.rmi.server.RMIClientSocketFactory, java.rmi.server.RMIServerSocketFactory) 0">
    <annotation name="org.jetbrains.annotations.NotNull"/>
  </item>
  <item name="java.rmi.activation.Activatable java.rmi.activation.ActivationID getID()">
    <annotation name="org.jetbrains.annotations.Contract">
      <val name="pure" val="true"/>
    </annotation>
  </item>
  <item name="java.rmi.activation.ActivationDesc ActivationDesc(java.rmi.activation.ActivationGroupID, java.lang.String, java.lang.String, java.rmi.MarshalledObject&lt;?&gt;)">
    <annotation name="org.jetbrains.annotations.LocalEffect"/>
  </item>
  <item name="java.rmi.activation.ActivationDesc ActivationDesc(java.rmi.activation.ActivationGroupID, java.lang.String, java.lang.String, java.rmi.MarshalledObject&lt;?&gt;) 0">
    <annotation name="org.jetbrains.annotations.NotNull"/>
  </item>
  <item name="java.rmi.activation.ActivationDesc ActivationDesc(java.rmi.activation.ActivationGroupID, java.lang.String, java.lang.String, java.rmi.MarshalledObject&lt;?&gt;, boolean)">
    <annotation name="org.jetbrains.annotations.LocalEffect"/>
  </item>
  <item name="java.rmi.activation.ActivationDesc ActivationDesc(java.rmi.activation.ActivationGroupID, java.lang.String, java.lang.String, java.rmi.MarshalledObject&lt;?&gt;, boolean) 0">
    <annotation name="org.jetbrains.annotations.NotNull"/>
  </item>
  <item name="java.rmi.activation.ActivationDesc boolean equals(java.lang.Object)">
    <annotation name="org.jetbrains.annotations.Contract">
      <val val="&quot;null-&gt;false&quot;"/>
    </annotation>
  </item>
  <item name="java.rmi.activation.ActivationDesc boolean equals(java.lang.Object) 0">
    <annotation name="org.jetbrains.annotations.Nullable"/>
  </item>
  <item name="java.rmi.activation.ActivationDesc boolean getRestartMode()">
    <annotation name="org.jetbrains.annotations.Contract">
      <val name="pure" val="true"/>
    </annotation>
  </item>
  <item name="java.rmi.activation.ActivationDesc java.lang.String getClassName()">
    <annotation name="org.jetbrains.annotations.Contract">
      <val name="pure" val="true"/>
    </annotation>
  </item>
  <item name="java.rmi.activation.ActivationDesc java.lang.String getLocation()">
    <annotation name="org.jetbrains.annotations.Contract">
      <val name="pure" val="true"/>
    </annotation>
  </item>
  <item name="java.rmi.activation.ActivationDesc java.rmi.MarshalledObject&lt;?&gt; getData()">
    <annotation name="org.jetbrains.annotations.Contract">
      <val name="pure" val="true"/>
    </annotation>
  </item>
  <item name="java.rmi.activation.ActivationDesc java.rmi.activation.ActivationGroupID getGroupID()">
    <annotation name="org.jetbrains.annotations.Contract">
      <val name="pure" val="true"/>
    </annotation>
  </item>
  <item name="java.rmi.activation.ActivationException java.lang.Throwable getCause()">
    <annotation name="org.jetbrains.annotations.Contract">
      <val name="pure" val="true"/>
    </annotation>
  </item>
  <item name="java.rmi.activation.ActivationGroup boolean inactiveObject(java.rmi.activation.ActivationID)">
    <annotation name="org.jetbrains.annotations.Contract">
      <val val="&quot;!null-&gt;true;null-&gt;true&quot;"/>
    </annotation>
  </item>
  <item name="java.rmi.activation.ActivationGroup java.rmi.activation.ActivationGroup createGroup(java.rmi.activation.ActivationGroupID, java.rmi.activation.ActivationGroupDesc, long) 0">
    <annotation name="org.jetbrains.annotations.NotNull"/>
  </item>
  <item name="java.rmi.activation.ActivationGroup java.rmi.activation.ActivationGroup createGroup(java.rmi.activation.ActivationGroupID, java.rmi.activation.ActivationGroupDesc, long) 1">
    <annotation name="org.jetbrains.annotations.NotNull"/>
  </item>
  <item name="java.rmi.activation.ActivationGroup java.rmi.activation.ActivationGroupID currentGroupID()">
    <annotation name="org.jetbrains.annotations.Contract">
      <val name="pure" val="true"/>
    </annotation>
  </item>
  <item name="java.rmi.activation.ActivationGroup void setSystem(java.rmi.activation.ActivationSystem) 0">
    <annotation name="org.jetbrains.annotations.Nullable"/>
  </item>
  <item name="java.rmi.activation.ActivationGroupDesc ActivationGroupDesc(java.lang.String, java.lang.String, java.rmi.MarshalledObject&lt;?&gt;, java.util.Properties, java.rmi.activation.ActivationGroupDesc.CommandEnvironment)">
    <annotation name="org.jetbrains.annotations.LocalEffect"/>
  </item>
  <item name="java.rmi.activation.ActivationGroupDesc ActivationGroupDesc(java.util.Properties, java.rmi.activation.ActivationGroupDesc.CommandEnvironment)">
    <annotation name="org.jetbrains.annotations.LocalEffect"/>
  </item>
  <item name="java.rmi.activation.ActivationGroupDesc boolean equals(java.lang.Object)">
    <annotation name="org.jetbrains.annotations.Contract">
      <val val="&quot;null-&gt;false&quot;"/>
    </annotation>
  </item>
  <item name="java.rmi.activation.ActivationGroupDesc boolean equals(java.lang.Object) 0">
    <annotation name="org.jetbrains.annotations.Nullable"/>
  </item>
  <item name="java.rmi.activation.ActivationGroupDesc java.lang.String getClassName()">
    <annotation name="org.jetbrains.annotations.Contract">
      <val name="pure" val="true"/>
    </annotation>
  </item>
  <item name="java.rmi.activation.ActivationGroupDesc java.lang.String getLocation()">
    <annotation name="org.jetbrains.annotations.Contract">
      <val name="pure" val="true"/>
    </annotation>
  </item>
  <item name="java.rmi.activation.ActivationGroupDesc java.rmi.MarshalledObject&lt;?&gt; getData()">
    <annotation name="org.jetbrains.annotations.Contract">
      <val name="pure" val="true"/>
    </annotation>
  </item>
  <item name="java.rmi.activation.ActivationGroupDesc java.rmi.activation.ActivationGroupDesc.CommandEnvironment getCommandEnvironment()">
    <annotation name="org.jetbrains.annotations.Contract">
      <val name="pure" val="true"/>
    </annotation>
  </item>
  <item name="java.rmi.activation.ActivationGroupDesc java.util.Properties getPropertyOverrides()">
    <annotation name="org.jetbrains.annotations.Nullable"/>
  </item>
  <item name="java.rmi.activation.ActivationGroupDesc.CommandEnvironment CommandEnvironment(java.lang.String, java.lang.String[]) 1">
    <annotation name="org.jetbrains.annotations.Nullable"/>
  </item>
  <item name="java.rmi.activation.ActivationGroupDesc.CommandEnvironment boolean equals(java.lang.Object)">
    <annotation name="org.jetbrains.annotations.Contract">
      <val val="&quot;null-&gt;false&quot;"/>
    </annotation>
  </item>
  <item name="java.rmi.activation.ActivationGroupDesc.CommandEnvironment boolean equals(java.lang.Object) 0">
    <annotation name="org.jetbrains.annotations.Nullable"/>
  </item>
  <item name="java.rmi.activation.ActivationGroupDesc.CommandEnvironment java.lang.String getCommandPath()">
    <annotation name="org.jetbrains.annotations.Contract">
      <val name="pure" val="true"/>
    </annotation>
  </item>
  <item name="java.rmi.activation.ActivationGroupDesc.CommandEnvironment void readObject(java.io.ObjectInputStream) 0">
    <annotation name="org.jetbrains.annotations.NotNull"/>
  </item>
  <item name="java.rmi.activation.ActivationGroupID boolean equals(java.lang.Object) 0">
    <annotation name="org.jetbrains.annotations.Nullable"/>
  </item>
  <item name="java.rmi.activation.ActivationGroupID int hashCode()">
    <annotation name="org.jetbrains.annotations.Contract">
      <val name="pure" val="true"/>
    </annotation>
  </item>
  <item name="java.rmi.activation.ActivationGroupID java.rmi.activation.ActivationSystem getSystem()">
    <annotation name="org.jetbrains.annotations.Contract">
      <val name="pure" val="true"/>
    </annotation>
  </item>
  <item name="java.rmi.activation.ActivationGroup_Stub ActivationGroup_Stub(java.rmi.server.RemoteRef)">
    <annotation name="org.jetbrains.annotations.LocalEffect"/>
  </item>
  <item name="java.rmi.activation.ActivationID boolean equals(java.lang.Object)">
    <annotation name="org.jetbrains.annotations.Contract">
      <val val="&quot;null-&gt;false&quot;"/>
    </annotation>
  </item>
  <item name="java.rmi.activation.ActivationID boolean equals(java.lang.Object) 0">
    <annotation name="org.jetbrains.annotations.Nullable"/>
  </item>
  <item name="java.rmi.activation.ActivationID int hashCode()">
    <annotation name="org.jetbrains.annotations.Contract">
      <val name="pure" val="true"/>
    </annotation>
  </item>
  <item name="java.rmi.activation.ActivationID void readObject(java.io.ObjectInputStream) 0">
    <annotation name="org.jetbrains.annotations.NotNull"/>
  </item>
  <item name="java.rmi.activation.ActivationID void writeObject(java.io.ObjectOutputStream) 0">
    <annotation name="org.jetbrains.annotations.NotNull"/>
  </item>
</root>
