<root>
  <item name="com.sun.security.sasl.digest.DigestMD5Base boolean isLws(byte)">
    <annotation name="org.jetbrains.annotations.Contract">
      <val name="pure" val="true"/>
    </annotation>
  </item>
  <item name="com.sun.security.sasl.digest.DigestMD5Base boolean needEscape(char)">
    <annotation name="org.jetbrains.annotations.Contract">
      <val name="pure" val="true"/>
    </annotation>
  </item>
  <item name="com.sun.security.sasl.digest.DigestMD5Base int skipLws(byte[], int)">
    <annotation name="org.jetbrains.annotations.Contract">
      <val name="pure" val="true"/>
    </annotation>
  </item>
  <item name="com.sun.security.sasl.digest.DigestMD5Base java.lang.Object getNegotiatedProperty(java.lang.String)">
    <annotation name="org.jetbrains.annotations.Contract">
      <val name="pure" val="true"/>
    </annotation>
  </item>
  <item name="com.sun.security.sasl.digest.DigestMD5Base java.lang.String getMechanismName()">
    <annotation name="org.jetbrains.annotations.Contract">
      <val name="pure" val="true"/>
    </annotation>
  </item>
  <item name="com.sun.security.sasl.digest.DigestMD5Base void dispose()">
    <annotation name="org.jetbrains.annotations.LocalEffect"/>
  </item>
  <item name="com.sun.security.sasl.digest.DigestMD5Base void setParityBit(byte[])">
    <annotation name="org.jetbrains.annotations.ParamChange" params="0"/>
  </item>
  <item name="com.sun.security.sasl.digest.DigestMD5Client boolean hasInitialResponse()">
    <annotation name="org.jetbrains.annotations.Contract">
      <val name="pure" val="true"/>
    </annotation>
  </item>
  <item name="com.sun.security.sasl.digest.DigestMD5Client int getNonceCount(byte[])">
    <annotation name="org.jetbrains.annotations.Contract">
      <val name="pure" val="true"/>
    </annotation>
  </item>
  <item name="com.sun.security.sasl.digest.DigestMD5Client java.lang.String findCipherAndStrength(byte[], java.lang.String[])">
    <annotation name="org.jetbrains.annotations.LocalEffect"/>
  </item>
  <item name="com.sun.security.sasl.digest.DigestMD5Server java.lang.String getAuthorizationID()">
    <annotation name="org.jetbrains.annotations.Contract">
      <val name="pure" val="true"/>
    </annotation>
  </item>
  <item name="com.sun.security.sasl.digest.FactoryImpl FactoryImpl()">
    <annotation name="org.jetbrains.annotations.Contract">
      <val name="pure" val="true"/>
    </annotation>
  </item>
</root>
