<root>
  <item name="com.sun.rowset.providers.RIOptimisticProvider int getDataSourceLock()">
    <annotation name="org.jetbrains.annotations.Contract">
      <val name="pure" val="true"/>
    </annotation>
  </item>
  <item name="com.sun.rowset.providers.RIOptimisticProvider int getProviderGrade()">
    <annotation name="org.jetbrains.annotations.Contract">
      <val name="pure" val="true"/>
    </annotation>
  </item>
  <item name="com.sun.rowset.providers.RIOptimisticProvider int supportsUpdatableView()">
    <annotation name="org.jetbrains.annotations.Contract">
      <val name="pure" val="true"/>
    </annotation>
  </item>
  <item name="com.sun.rowset.providers.RIOptimisticProvider java.lang.String getProviderID()">
    <annotation name="org.jetbrains.annotations.Contract">
      <val name="pure" val="true"/>
    </annotation>
  </item>
  <item name="com.sun.rowset.providers.RIOptimisticProvider java.lang.String getVendor()">
    <annotation name="org.jetbrains.annotations.Contract">
      <val name="pure" val="true"/>
    </annotation>
  </item>
  <item name="com.sun.rowset.providers.RIOptimisticProvider java.lang.String getVersion()">
    <annotation name="org.jetbrains.annotations.Contract">
      <val name="pure" val="true"/>
    </annotation>
  </item>
  <item name="com.sun.rowset.providers.RIOptimisticProvider javax.sql.RowSetReader getRowSetReader()">
    <annotation name="org.jetbrains.annotations.Contract">
      <val name="pure" val="true"/>
    </annotation>
  </item>
  <item name="com.sun.rowset.providers.RIOptimisticProvider void readObject(java.io.ObjectInputStream) 0">
    <annotation name="org.jetbrains.annotations.NotNull"/>
  </item>
  <item name="com.sun.rowset.providers.RIXMLProvider int getDataSourceLock()">
    <annotation name="org.jetbrains.annotations.Contract">
      <val name="pure" val="true"/>
    </annotation>
  </item>
  <item name="com.sun.rowset.providers.RIXMLProvider int getProviderGrade()">
    <annotation name="org.jetbrains.annotations.Contract">
      <val name="pure" val="true"/>
    </annotation>
  </item>
  <item name="com.sun.rowset.providers.RIXMLProvider int supportsUpdatableView()">
    <annotation name="org.jetbrains.annotations.Contract">
      <val name="pure" val="true"/>
    </annotation>
  </item>
  <item name="com.sun.rowset.providers.RIXMLProvider java.lang.String getProviderID()">
    <annotation name="org.jetbrains.annotations.Contract">
      <val name="pure" val="true"/>
    </annotation>
  </item>
  <item name="com.sun.rowset.providers.RIXMLProvider java.lang.String getVendor()">
    <annotation name="org.jetbrains.annotations.Contract">
      <val name="pure" val="true"/>
    </annotation>
  </item>
  <item name="com.sun.rowset.providers.RIXMLProvider java.lang.String getVersion()">
    <annotation name="org.jetbrains.annotations.Contract">
      <val name="pure" val="true"/>
    </annotation>
  </item>
  <item name="com.sun.rowset.providers.RIXMLProvider javax.sql.RowSetReader getRowSetReader()">
    <annotation name="org.jetbrains.annotations.Contract">
      <val name="pure" val="true"/>
    </annotation>
    <annotation name="org.jetbrains.annotations.Nullable"/>
  </item>
  <item name="com.sun.rowset.providers.RIXMLProvider javax.sql.RowSetWriter getRowSetWriter()">
    <annotation name="org.jetbrains.annotations.Contract">
      <val name="pure" val="true"/>
    </annotation>
    <annotation name="org.jetbrains.annotations.Nullable"/>
  </item>
  <item name="com.sun.rowset.providers.RIXMLProvider javax.sql.rowset.spi.XmlReader getXmlReader()">
    <annotation name="org.jetbrains.annotations.Contract">
      <val name="pure" val="true"/>
    </annotation>
  </item>
  <item name="com.sun.rowset.providers.RIXMLProvider javax.sql.rowset.spi.XmlWriter getXmlWriter()">
    <annotation name="org.jetbrains.annotations.Contract">
      <val name="pure" val="true"/>
    </annotation>
  </item>
  <item name="com.sun.rowset.providers.RIXMLProvider void setXmlReader(javax.sql.rowset.spi.XmlReader)">
    <annotation name="org.jetbrains.annotations.LocalEffect"/>
  </item>
  <item name="com.sun.rowset.providers.RIXMLProvider void setXmlWriter(javax.sql.rowset.spi.XmlWriter)">
    <annotation name="org.jetbrains.annotations.LocalEffect"/>
  </item>
</root>
